Metadata-Version: 2.1
Name: PlexAPI-backport
Version: 4.15.10
Summary: Python bindings for the Plex API.
Home-page: https://github.com/LizardByte/python-plexapi-backport
Author: LizardByte
Author-email: LizardByte@github.com
License: UNKNOWN
Keywords: plex,api
Platform: UNKNOWN
Classifier: Operating System :: OS Independent
Classifier: Programming Language :: Python :: 2.7
Classifier: Programming Language :: Python :: 3
Classifier: License :: OSI Approved :: BSD License
Requires-Python: >=2.7
Requires-Dist: future (==0.18.3)
Requires-Dist: six (==1.16.0)
Requires-Dist: configparser (==4.0.2) ; python_version < "3"
Requires-Dist: requests (==2.27.1) ; python_version < "3"
Requires-Dist: backports.shutil-which (==3.5.2) ; python_version < "3.3"
Requires-Dist: qualname (==0.1.0) ; python_version < "3.3"
Requires-Dist: pathlib2 (==2.3.7.post1) ; python_version < "3.4"
Requires-Dist: typing ; python_version < "3.5"
Requires-Dist: backports.datetime-timestamp (==1.2) ; python_version < "3.8"
Requires-Dist: cached-property (==1.5.2) ; python_version < "3.8"
Requires-Dist: requests ; python_version >= "3.8"
Requires-Dist: backports.datetime-timestamp (==1.3.0) ; python_version >= "3.8"
Provides-Extra: alert
Requires-Dist: websocket-client (>=0.59.0) ; extra == 'alert'
